<?xml version="1.0" encoding="utf-8"?>
<eSocial xmlns="http://www.esocial.gov.br/schema/evt/evtContProc/v_S_01_03_00" xmlns:xsi="http://www.w3.org/2001/XMLSchema-instance" xsi:schemaLocation="http://www.esocial.gov.br/schema/evt/evtContProc/v_S_01_03_00 ../v_S_01_03_00/evtContProc.xsd">
    <evtContProc Id="ID9999999999999999999999999999999999">
        <ideEvento>
            <indRetif>1</indRetif>
            <nrRecibo>1.9.9999999999999999999</nrRecibo>
            <tpAmb>1</tpAmb>
            <procEmi>1</procEmi>
            <verProc>99999999999999999999</verProc>
        </ideEvento>
        <ideEmpregador>
            <tpInsc>1</tpInsc>
            <nrInsc>99999999999999</nrInsc>
        </ideEmpregador>
        <ideProc>
            <nrProcTrab>99999999999999999999</nrProcTrab>
            <perApurPgto>2999-12</perApurPgto>
            <ideSeqProc>1</ideSeqProc>
            <obs>999</obs>
        </ideProc>
        <ideTrab cpfTrab="99999999999">
            <calcTrib perRef="2999-12" vrBcCpMensal="999999999999.99" vrBcCp13="999999999999.99">
                <infoCRContrib tpCR="999999" vrCR="999999999999.99" />
            </calcTrib>
            <infoCRIRRF tpCR="593656" vrCR="999999999999.99" vrCR13="999999999999.99">
                <infoIR vrRendTrib="999999999999.99" vrRendTrib13="999999999999.99" vrRendMoleGrave="999999999999.99" vrRendMoleGrave13="999999999999.99" vrRendIsen65="999999999999.99" vrRendIsen65Dec="999999999999.99" vrJurosMora="999999999999.99" vrJurosMora13="999999999999.99" vrRendIsenNTrib="999999999999.99" descIsenNTrib="999999999999.99" vrPrevOficial="999999999999.99" vrPrevOficial13="999999999999.99">
                    <rendIsen0561 vlrDiarias="999999999999.99" vlrAjudaCusto="999999999999.99" vlrIndResContrato="999999999999.99" vlrAbonoPec="999999999999.99" vlrAuxMoradia="999999999999.99" />
                </infoIR>
                <infoRRA descRRA="99999999999999999999999999999999999999999999999999" qtdMesesRRA="999.9">
                    <despProcJud vlrDespCustas="999999999999.99" vlrDespAdvogados="999999999999.99" />
                    <ideAdv tpInsc="1" nrInsc="99999999999999" vlrAdv="999999999999.99" />
                </infoRRA>
                <dedDepen tpRend="11" cpfDep="99999999999" vlrDeducao="999999999999.99" />
                <penAlim tpRend="11" cpfDep="99999999999" vlrPensao="999999999999.99" />
                <infoProcRet tpProcRet="1" nrProcRet="999999999999999999999" codSusp="99999999999999">
                    <infoValores indApuracao="1" vlrNRetido="999999999999.99" vlrDepJud="999999999999.99" vlrCmpAnoCal="999999999999.99" vlrCmpAnoAnt="999999999999.99" vlrRendSusp="999999999999.99">
                        <dedSusp indTpDeducao="1" vlrDedSusp="999999999999.99">
                            <benefPen cpfDep="99999999999" vlrDepenSusp="999999999999.99" />
                        </dedSusp>
                    </infoValores>
                </infoProcRet>
            </infoCRIRRF>
            <infoIRComplem dtLaudo="9999-12-31">
                <infoDep cpfDep="99999999999" dtNascto="9999-12-31" nome="9999999999999999999999999999999999999999999999999999999999999999999999" depIRRF="S" tpDep="99" descrDep="9999999999999999999999999999999999999999999999999999999999999999999999999999999999999999999999999999" />
            </infoIRComplem>
        </ideTrab>
    </evtContProc>
    <Signature xmlns="http://www.w3.org/2000/09/xmldsig#">
        <SignedInfo>
            <CanonicalizationMethod Algorithm="http://www.w3.org/TR/2001/REC-xml-c14n-20010315" />
            <SignatureMethod Algorithm="http://www.w3.org/2001/04/xmldsig-more#rsa-sha256" />
            <Reference URI="">
                <Transforms>
                    <Transform Algorithm="http://www.w3.org/2000/09/xmldsig#enveloped-signature" />
                    <Transform Algorithm="http://www.w3.org/TR/2001/REC-xml-c14n-20010315" />
                </Transforms>
                <DigestMethod Algorithm="http://www.w3.org/2001/04/xmlenc#sha256" />
                <DigestValue></DigestValue>
            </Reference>
        </SignedInfo>
        <SignatureValue></SignatureValue>
        <KeyInfo>
            <X509Data>
                <X509Certificate></X509Certificate>
            </X509Data>
        </KeyInfo>
    </Signature>
</eSocial>